README.rst
bot.py
setup.py
charlybot.egg-info/PKG-INFO
charlybot.egg-info/SOURCES.txt
charlybot.egg-info/dependency_links.txt
charlybot.egg-info/top_level.txt