Metadata-Version: 1.0
Name: charlybot
Version: 0.2
Summary: bot discord.py
Home-page: https://github.com/charlyDevor/charly-bot
Author: charlyDevor
Author-email: UNKNOWN
License: UNKNOWN
Platform: UNKNOWN
